MANIFEST.in
README.rst
setup.py
worldmor/__init__.py
worldmor/__main__.py
worldmor/about.py
worldmor/constants.py
worldmor/gui.py
worldmor.egg-info/PKG-INFO
worldmor.egg-info/SOURCES.txt
worldmor.egg-info/dependency_links.txt
worldmor.egg-info/entry_points.txt
worldmor.egg-info/not-zip-safe
worldmor.egg-info/requires.txt
worldmor.egg-info/top_level.txt
worldmor/game/game.c
worldmor/game/game.cpython-37m-x86_64-linux-gnu.so
worldmor/game/game.pyx
worldmor/gui/fullscreen_dialog.ui
worldmor/gui/game_over.ui
worldmor/gui/mainwindow.ui
worldmor/img/blood.svg
worldmor/img/bullet.svg
worldmor/img/e1.svg
worldmor/img/e2.svg
worldmor/img/e3.svg
worldmor/img/e4.svg
worldmor/img/ex.svg
worldmor/img/g1.svg
worldmor/img/g2.svg
worldmor/img/g3.svg
worldmor/img/g4.svg
worldmor/img/g5.svg
worldmor/img/grass.svg
worldmor/img/health.svg
worldmor/img/player.svg
worldmor/img/wall.svg
worldmor/img/worldmor.svg