Metadata-Version: 1.1
Name: worldmor
Version: 0.3.1
Summary: Arcade 2D survival game.
Home-page: https://github.com/martilad/worldmor
Author: Ladislav Martínek
Author-email: martilad@fit.cvut.cz
License: GPLv3
Keywords: Worldmor,game,arcade,survival
Platform: UNKNOWN
Classifier: Intended Audience :: Education
Classifier: Intended Audience :: Information Technology
Classifier: License :: OSI Approved :: GNU General Public License v3 (GPLv3)
Classifier: Framework :: Pytest
Classifier: Framework :: Sphinx
Classifier: Topic :: Games/Entertainment
Classifier: Topic :: Games/Entertainment :: Arcade
Classifier: Programming Language :: Cython
Classifier: Programming Language :: Python
Classifier: Programming Language :: Python :: 3
Classifier: Programming Language :: Python :: 3.6
Classifier: Programming Language :: Python :: 3.7
Classifier: Natural Language :: English
Classifier: Topic :: Software Development
Classifier: Development Status :: 3 - Alpha
